greattunes/__init__.py
greattunes/_acq_func.py
greattunes/_best_response.py
greattunes/_campaign.py
greattunes/_initializers.py
greattunes/_modeling.py
greattunes/_observe.py
greattunes/_plot.py
greattunes/_validators.py
greattunes/_version.py
greattunes/data_format_mappings.py
greattunes/utils.py
greattunes/custom_models/__init__.py
greattunes/custom_models/simple_matern_model.py
greattunes/transformed_kernel_models/GPregression.py
greattunes/transformed_kernel_models/__init__.py
greattunes/transformed_kernel_models/transformation.py
greattunes-0.0.7.dist-info/LICENSE
greattunes-0.0.7.dist-info/METADATA
greattunes-0.0.7.dist-info/WHEEL
greattunes-0.0.7.dist-info/top_level.txt
greattunes-0.0.7.dist-info/RECORD
