Metadata-Version: 2.1
Name: greattunes
Version: 0.0.7
Summary: Toolset for easy execution of Bayesian optimization for either step-by-step or closed-loop needs.
Home-page: https://github.com/svedel/greattunes
Author: Søren Vedel
License: UNKNOWN
Platform: UNKNOWN
Classifier: Programming Language :: Python :: 3
Classifier: License :: OSI Approved :: MIT License
Classifier: Intended Audience :: Developers
Classifier: Intended Audience :: Science/Research
Classifier: Operating System :: OS Independent
Requires-Python: >=3.7
License-File: LICENSE
Requires-Dist: botorch (==0.2.1)
Requires-Dist: gpytorch (==1.1.1)
Requires-Dist: matplotlib (==3.3.2)
Requires-Dist: numpy (==1.19.1)
Requires-Dist: pandas (==1.2.3)
Requires-Dist: pytz (==2021.1)
